{
  "Lauren": [
    {
      "id": "9799d31b258b",
      "title": "6-Week Postpartum Core & Resilience Block",
      "body": "Goal: Reconnect with core, rebuild pelvic floor awareness, manage energy around your cycle, stay strong for four boys and a 13-month-old.\n\nWEEKLY STRUCTURE:\n\nMonday — FORTITUDE (Family Run)\n11:00 AM: Family Run (JP & Joseph run 1.5-2mi; you run/walk intervals 0.75-1mi for ankle loading & core engagement; Michael bikes/scoots; James in stroller)\n- Warm-up: 5min easy pace\n- Main work: 18min mixed run/walk intervals\n- Cool-down: 5min walk & breathe together\n- Cycle note: Follicular phase (Days 1-14): push intervals. Luteal phase (Days 15-28): extend warm-up & cool-down, reduce intensity.\n\nWednesday — JUSTICE (Family Strength + Skill Block)\n9:00 AM: 20-30min bodyweight strength circuit (you + boys together, scaled per age)\n- Core work: bird dogs, dead bugs, side planks (hold 20-30sec)\n- Lower body: squats, lunges, step-ups (using stairs or low bench)\n- Upper body: push-ups (incline or wall), rows (resistance band or towel)\n- Pelvic floor activation: bridges, glute squeezes (2sec hold, 2sec release, 10 reps)\n- Cycle note: Follicular & ovulatory (Days 1-14): 3 sets x 10-12 reps, heavier load. Luteal (Days 15-28): 2 sets x 12-15 reps, lighter load, focus on form.\n\nFriday — PRUDENCE (Family Adventure Block)\n11:00 AM: Structured walk or outdoor exploration (20-30min)\n- Default: Easy walk (hills optional)\n- When weather permits: Hike, park exploration, or yard project\n- Michael bikes/scoots or explores. James in stroller.\n- Goal: Movement + family time, not intensity\n- Cycle note: Days 23-28 (late luteal): Keep this easy. This is your wind-down week.\n\nSaturday — Hinge Health Ankle PT + Flexibility\n8:30 PM: 10min Hinge Health rotating ankle video (standing or seated, your choice)\nAdd: 5min gentle stretching (hip openers, spinal twists, child's pose)\n- Cycle note: All phases. Non-negotiable for ankle stability post-pregnancy.\n\nDAILY MINIMUM (if structured workouts don't happen):\n- 10-15min walk with stroller or alone\n- 5min pelvic floor breathing (4-count inhale, 6-count exhale, 10 reps)\n- Hydrate: 3-4L water daily, more on exercise days\n\nPROGRESSION (over 6 weeks):\nWeeks 1-2: Learn the movements. Focus on form, not reps. Add 1 rep per set each week.\nWeeks 3-4: Increase reps or hold times. Consider adding a resistance band for rows/chest press.\nWeeks 5-6: Increase circuit rounds (2 → 3 sets) or add tempo (2-second lower on squats/lunges).\n\nCYCLE AWARENESS:\nFollicular Phase (Days 1-14): Energy rising. Intensity up. Push intervals on Monday, heavier loads on Wednesday. 3 sets x 10-12 reps. Longer cardio windows.\nOvulatory Phase (Days 14-15): Peak energy. Peak performance window. Go hard if you want to.\nLuteal Phase (Days 16-28): Energy declining. Simplify. Extend warm-ups & cool-downs. Lighter loads, more reps. 2 sets x 12-15 reps. Shorter, strategic workouts. Days 23-28 (late luteal): Grace, gentleness, stretching.\n\nNOTES:\n- Family runs count as PE for JP & Joseph — coordinate with Father Gregory.\n- Core work is non-negotiable — 13 months postpartum, your pelvic floor and deep core still need attention.\n- Ankle loading on Mondays rebuilds ankle stability for future strength work.\n- If you skip a day, don't guilt spiral. Pick it back up the next day. Consistency over perfection.\n- Listen to your body. Rest counts as recovery.",
      "saved_at": "2026-04-28T21:05:19"
    }
  ]
}